AUTHORS
MANIFEST.in
README.rst
setup.py
django_pipeline_eco.egg-info/PKG-INFO
django_pipeline_eco.egg-info/SOURCES.txt
django_pipeline_eco.egg-info/dependency_links.txt
django_pipeline_eco.egg-info/not-zip-safe
django_pipeline_eco.egg-info/requires.txt
django_pipeline_eco.egg-info/top_level.txt
pipeline_eco/__init__.py
pipeline_eco/compiler.py