Metadata-Version: 1.0
Name: django-pipeline-eco
Version: 0.1.4
Summary: django-pipeline compiler for eco templates
Home-page: https://github.com/vshjxyz/django-pipeline-eco
Author: Luca Del Bianco
Author-email: vshjxyz@gmail.com
License: UNKNOWN
Platform: UNKNOWN
Classifier: Environment :: Web Environment
Classifier: Intended Audience :: Developers
Classifier: License :: OSI Approved :: MIT License
Classifier: Operating System :: OS Independent
Classifier: Programming Language :: Python
Classifier: Topic :: Utilities
